screepsapi/__init__.py
screepsapi/screepsapi.py
screepsapi-0.5.1.dist-info/DESCRIPTION.rst
screepsapi-0.5.1.dist-info/METADATA
screepsapi-0.5.1.dist-info/RECORD
screepsapi-0.5.1.dist-info/WHEEL
screepsapi-0.5.1.dist-info/metadata.json
screepsapi-0.5.1.dist-info/top_level.txt
