Metadata-Version: 2.0
Name: screepsapi
Version: 0.5.1
Summary: Screeps Unofficial Client for the Unofficial API
Home-page: https://github.com/screepers/screeps-api
Author: Robert Hafner, dzhu
Author-email: tedivm@tedivm.com
License: UNKNOWN
Download-URL: https://github.com/screepers/screeps-api/archive/v0.5.1.tar.gz
Keywords: screeps api
Platform: UNKNOWN
Classifier: Development Status :: 4 - Beta
Classifier: License :: OSI Approved :: MIT License
Classifier: Intended Audience :: Developers
Classifier: Programming Language :: Python :: 3
Classifier: Programming Language :: Python :: 2
Requires-Python: >=2
Requires-Dist: nose
Requires-Dist: requires
Requires-Dist: requests (<3,>=2.10.0)
Requires-Dist: websocket-client
Provides-Extra: dev
Requires-Dist: pypandoc; extra == 'dev'
Requires-Dist: twine; extra == 'dev'
Requires-Dist: wheel; extra == 'dev'
